LICENSE
README.md
setup.py
PyPasser.egg-info/PKG-INFO
PyPasser.egg-info/SOURCES.txt
PyPasser.egg-info/dependency_links.txt
PyPasser.egg-info/requires.txt
PyPasser.egg-info/top_level.txt
pypasser/__init__.py
pypasser/exceptions.py
pypasser/session.py
pypasser/structs.py
pypasser/utils.py
pypasser/reCaptchaV2/__init__.py
pypasser/reCaptchaV3/__init__.py
pypasser/reCaptchaV3/constants.py